{
  "site_updated_at": "2026-03-12",
  "extracted_at": "2026-03-13 07:19:36",
  "search_context": {
    "annee": "2025",
    "tgeo": "fe",
    "codegeo": "99",
    "SePP": "0",
    "SeTailEt": "0",
    "catmaj": "01",
    "gn": "0118",
    "gpmedeco": "0118PC1"
  },
  "data": [
    {
      "finess": "130041916",
      "raison_sociale": "CH DU PAYS D'AIX CHI AIX PERTUIS",
      "categorie": "CH",
      "periode": "M12",
      "nb_journees_total": "52",
      "nb_journees_hc": "52",
      "nb_journees_hp": "0",
      "sexe_ratio": "73.1%",
      "age_moyen": "7.62",
      "avq_physique": "16",
      "avq_relationnel": "8",
      "nb_actes_csarr": "1.69"
    },
    {
      "finess": "130043508",
      "raison_sociale": "UNITÉ PEDIATRIQUE POMPONIANA MARSEILLE",
      "categorie": "PSPH/EBNL",
      "periode": "M12",
      "nb_journees_total": "88",
      "nb_journees_hc": "88",
      "nb_journees_hp": "0",
      "sexe_ratio": "72.7%",
      "age_moyen": "10.68",
      "avq_physique": "14.28",
      "avq_relationnel": "6.81",
      "nb_actes_csarr": "4.28"
    },
    {
      "finess": "140019175",
      "raison_sociale": "CRF MANOIR D'APRIGNY",
      "categorie": "PSPH/EBNL",
      "periode": "M12",
      "nb_journees_total": "277",
      "nb_journees_hc": "277",
      "nb_journees_hp": "0",
      "sexe_ratio": "100%",
      "age_moyen": "9.11",
      "avq_physique": "15.66",
      "avq_relationnel": "7.91",
      "nb_actes_csarr": "2.12"
    },
    {
      "finess": "170780803",
      "raison_sociale": "CENTRE DE RÉADAPTATION D'OLERON",
      "categorie": "PSPH/EBNL",
      "periode": "M12",
      "nb_journees_total": "66",
      "nb_journees_hc": "66",
      "nb_journees_hp": "0",
      "sexe_ratio": "69.7%",
      "age_moyen": "11.85",
      "avq_physique": "15.71",
      "avq_relationnel": "7.2",
      "nb_actes_csarr": "1.26"
    },
    {
      "finess": "220000103",
      "raison_sociale": "CH LANNION",
      "categorie": "CH",
      "periode": "M12",
      "nb_journees_total": "438",
      "nb_journees_hc": "438",
      "nb_journees_hp": "0",
      "sexe_ratio": "100%",
      "age_moyen": "8.42",
      "avq_physique": "16",
      "avq_relationnel": "8",
      "nb_actes_csarr": "1.24"
    },
    {
      "finess": "250000544",
      "raison_sociale": "CRRF LES SALINS DE BREGILLE",
      "categorie": "PSPH/EBNL",
      "periode": "M12",
      "nb_journees_total": "1 à 10",
      "nb_journees_hc": "1 à 10",
      "nb_journees_hp": "0",
      "sexe_ratio": "NA",
      "age_moyen": "NA",
      "avq_physique": "NA",
      "avq_relationnel": "NA",
      "nb_actes_csarr": "NA"
    },
    {
      "finess": "290000827",
      "raison_sociale": "CHM DE ROSCOFF SITE DE TY-YANN",
      "categorie": "PSPH/EBNL",
      "periode": "M12",
      "nb_journees_total": "262",
      "nb_journees_hc": "262",
      "nb_journees_hp": "0",
      "sexe_ratio": "18.7%",
      "age_moyen": "13.87",
      "avq_physique": "14.81",
      "avq_relationnel": "7.82",
      "nb_actes_csarr": "0.56"
    },
    {
      "finess": "300780038",
      "raison_sociale": "CHU NIMES",
      "categorie": "CHR/U",
      "periode": "M12",
      "nb_journees_total": "11",
      "nb_journees_hc": "11",
      "nb_journees_hp": "0",
      "sexe_ratio": "100%",
      "age_moyen": "16",
      "avq_physique": "16",
      "avq_relationnel": "8",
      "nb_actes_csarr": "0.27"
    },
    {
      "finess": "310781422",
      "raison_sociale": "CENTRE PAUL DOTTIN",
      "categorie": "PSPH/EBNL",
      "periode": "M12",
      "nb_journees_total": "25",
      "nb_journees_hc": "25",
      "nb_journees_hp": "0",
      "sexe_ratio": "12%",
      "age_moyen": "9.52",
      "avq_physique": "15.88",
      "avq_relationnel": "7.12",
      "nb_actes_csarr": "0.8"
    },
    {
      "finess": "310792874",
      "raison_sociale": "CENTRE ANDRE BOUSQUAIROL",
      "categorie": "PSPH/EBNL",
      "periode": "M12",
      "nb_journees_total": "1 à 10",
      "nb_journees_hc": "1 à 10",
      "nb_journees_hp": "0",
      "sexe_ratio": "NA",
      "age_moyen": "NA",
      "avq_physique": "NA",
      "avq_relationnel": "NA",
      "nb_actes_csarr": "NA"
    },
    {
      "finess": "320780323",
      "raison_sociale": "CRF DE ROQUETAILLADE",
      "categorie": "PSPH/EBNL",
      "periode": "M12",
      "nb_journees_total": "296",
      "nb_journees_hc": "296",
      "nb_journees_hp": "0",
      "sexe_ratio": "87.2%",
      "age_moyen": "15.47",
      "avq_physique": "15.56",
      "avq_relationnel": "7.75",
      "nb_actes_csarr": "0.77"
    },
    {
      "finess": "340000025",
      "raison_sociale": "INSTITUT SAINT PIERRE",
      "categorie": "PSPH/EBNL",
      "periode": "M12",
      "nb_journees_total": "156",
      "nb_journees_hc": "156",
      "nb_journees_hp": "0",
      "sexe_ratio": "54.5%",
      "age_moyen": "9.04",
      "avq_physique": "14.93",
      "avq_relationnel": "7.13",
      "nb_actes_csarr": "8.78"
    },
    {
      "finess": "350005179",
      "raison_sociale": "CHRU DE RENNES",
      "categorie": "CHR/U",
      "periode": "M12",
      "nb_journees_total": "525",
      "nb_journees_hc": "525",
      "nb_journees_hp": "0",
      "sexe_ratio": "83%",
      "age_moyen": "9.85",
      "avq_physique": "15.93",
      "avq_relationnel": "7.93",
      "nb_actes_csarr": "6.18"
    },
    {
      "finess": "370000481",
      "raison_sociale": "CHU DE TOURS",
      "categorie": "CHR/U",
      "periode": "M12",
      "nb_journees_total": "23",
      "nb_journees_hc": "23",
      "nb_journees_hp": "0",
      "sexe_ratio": "0%",
      "age_moyen": "3",
      "avq_physique": "16",
      "avq_relationnel": "8",
      "nb_actes_csarr": "2.26"
    },
    {
      "finess": "380780080",
      "raison_sociale": "CHU GRENOBLE ALPES",
      "categorie": "CHR/U",
      "periode": "M12",
      "nb_journees_total": "22",
      "nb_journees_hc": "22",
      "nb_journees_hp": "0",
      "sexe_ratio": "0%",
      "age_moyen": "7",
      "avq_physique": "16",
      "avq_relationnel": "8",
      "nb_actes_csarr": "2.64"
    },
    {
      "finess": "420784878",
      "raison_sociale": "CHU SAINT ETIENNE",
      "categorie": "CHR/U",
      "periode": "M12",
      "nb_journees_total": "152",
      "nb_journees_hc": "152",
      "nb_journees_hp": "0",
      "sexe_ratio": "72.4%",
      "age_moyen": "8.44",
      "avq_physique": "16",
      "avq_relationnel": "8",
      "nb_actes_csarr": "5.53"
    },
    {
      "finess": "440043123",
      "raison_sociale": "E.S.E.A.N",
      "categorie": "PSPH/EBNL",
      "periode": "M12",
      "nb_journees_total": "54",
      "nb_journees_hc": "54",
      "nb_journees_hp": "0",
      "sexe_ratio": "63%",
      "age_moyen": "6.06",
      "avq_physique": "15.93",
      "avq_relationnel": "7.63",
      "nb_actes_csarr": "3.09"
    },
    {
      "finess": "490531910",
      "raison_sociale": "SSR LES CAPUCINS",
      "categorie": "PSPH/EBNL",
      "periode": "M12",
      "nb_journees_total": "95",
      "nb_journees_hc": "95",
      "nb_journees_hp": "0",
      "sexe_ratio": "29.5%",
      "age_moyen": "13.59",
      "avq_physique": "15.85",
      "avq_relationnel": "7.08",
      "nb_actes_csarr": "2.17"
    },
    {
      "finess": "510000029",
      "raison_sociale": "CHR DE REIMS",
      "categorie": "CHR/U",
      "periode": "M12",
      "nb_journees_total": "1 à 10",
      "nb_journees_hc": "1 à 10",
      "nb_journees_hp": "0",
      "sexe_ratio": "NA",
      "age_moyen": "NA",
      "avq_physique": "NA",
      "avq_relationnel": "NA",
      "nb_actes_csarr": "NA"
    },
    {
      "finess": "540013737",
      "raison_sociale": "CRE FLAVIGNY IRR",
      "categorie": "PSPH/EBNL",
      "periode": "M12",
      "nb_journees_total": "154",
      "nb_journees_hc": "154",
      "nb_journees_hp": "0",
      "sexe_ratio": "73.4%",
      "age_moyen": "8.77",
      "avq_physique": "15.33",
      "avq_relationnel": "6.09",
      "nb_actes_csarr": "2.51"
    },
    {
      "finess": "560002024",
      "raison_sociale": "CRRF KERPAPE",
      "categorie": "PSPH/EBNL",
      "periode": "M12",
      "nb_journees_total": "87",
      "nb_journees_hc": "87",
      "nb_journees_hp": "0",
      "sexe_ratio": "87.4%",
      "age_moyen": "13.78",
      "avq_physique": "13.29",
      "avq_relationnel": "6.6",
      "nb_actes_csarr": "3.61"
    },
    {
      "finess": "590782611",
      "raison_sociale": "SSR PEDIATRIQUE MARC SAUTELET",
      "categorie": "PSPH/EBNL",
      "periode": "M12",
      "nb_journees_total": "44",
      "nb_journees_hc": "44",
      "nb_journees_hp": "0",
      "sexe_ratio": "100%",
      "age_moyen": "15.45",
      "avq_physique": "12.36",
      "avq_relationnel": "8",
      "nb_actes_csarr": "5.02"
    },
    {
      "finess": "590785424",
      "raison_sociale": "CENTRE L'ADAPT DE CAMBRAI",
      "categorie": "PSPH/EBNL",
      "periode": "M12",
      "nb_journees_total": "1 à 10",
      "nb_journees_hc": "1 à 10",
      "nb_journees_hp": "0",
      "sexe_ratio": "NA",
      "age_moyen": "NA",
      "avq_physique": "NA",
      "avq_relationnel": "NA",
      "nb_actes_csarr": "NA"
    },
    {
      "finess": "610780389",
      "raison_sociale": "CMPR LA CLAIRIERE FLERS",
      "categorie": "PSPH/EBNL",
      "periode": "M12",
      "nb_journees_total": "95",
      "nb_journees_hc": "95",
      "nb_journees_hp": "0",
      "sexe_ratio": "53.7%",
      "age_moyen": "13.29",
      "avq_physique": "14.51",
      "avq_relationnel": "7.19",
      "nb_actes_csarr": "1.99"
    },
    {
      "finess": "620000026",
      "raison_sociale": "ÉTABLISSEMENT HOPALE CTRE CALOT - HELIO",
      "categorie": "PSPH/EBNL",
      "periode": "M12",
      "nb_journees_total": "1 à 10",
      "nb_journees_hc": "1 à 10",
      "nb_journees_hp": "0",
      "sexe_ratio": "NA",
      "age_moyen": "NA",
      "avq_physique": "NA",
      "avq_relationnel": "NA",
      "nb_actes_csarr": "NA"
    },
    {
      "finess": "620105973",
      "raison_sociale": "CENTRE ANTOINE DE SAINT-EXUPERY - VENDIN LE VIEIL",
      "categorie": "PSPH/EBNL",
      "periode": "M12",
      "nb_journees_total": "581",
      "nb_journees_hc": "581",
      "nb_journees_hp": "0",
      "sexe_ratio": "98.6%",
      "age_moyen": "4.35",
      "avq_physique": "16",
      "avq_relationnel": "8",
      "nb_actes_csarr": "2.67"
    },
    {
      "finess": "630781755",
      "raison_sociale": "CENTRE MÉDICAL INFANTILE DE ROMAGNAT",
      "categorie": "PSPH/EBNL",
      "periode": "M12",
      "nb_journees_total": "395",
      "nb_journees_hc": "395",
      "nb_journees_hp": "0",
      "sexe_ratio": "68.9%",
      "age_moyen": "5.84",
      "avq_physique": "16",
      "avq_relationnel": "7.98",
      "nb_actes_csarr": "1.82"
    },
    {
      "finess": "640780904",
      "raison_sociale": "LE NID BEARNAIS - SSR PEDIATRIQUE",
      "categorie": "PSPH/EBNL",
      "periode": "M12",
      "nb_journees_total": "14",
      "nb_journees_hc": "14",
      "nb_journees_hp": "0",
      "sexe_ratio": "100%",
      "age_moyen": "11.64",
      "avq_physique": "16",
      "avq_relationnel": "8",
      "nb_actes_csarr": "0.57"
    },
    {
      "finess": "670780121",
      "raison_sociale": "UGECAM-C.R.F. CLEMENCEAU STRASBOURG",
      "categorie": "PSPH/EBNL",
      "periode": "M12",
      "nb_journees_total": "15",
      "nb_journees_hc": "15",
      "nb_journees_hp": "0",
      "sexe_ratio": "100%",
      "age_moyen": "6.13",
      "avq_physique": "16",
      "avq_relationnel": "7",
      "nb_actes_csarr": "2.87"
    },
    {
      "finess": "690000427",
      "raison_sociale": "CENTRE MÉDICO-CHIRURGICAL ET DE RÉÉDAPTATIION LES MASSUES",
      "categorie": "PSPH/EBNL",
      "periode": "M12",
      "nb_journees_total": "1015",
      "nb_journees_hc": "1015",
      "nb_journees_hp": "0",
      "sexe_ratio": "49.3%",
      "age_moyen": "11.41",
      "avq_physique": "14.26",
      "avq_relationnel": "6.29",
      "nb_actes_csarr": "6.54"
    },
    {
      "finess": "690041132",
      "raison_sociale": "MEDIPOLE HÔPITAL MUTUALISTE",
      "categorie": "PSPH/EBNL",
      "periode": "M12",
      "nb_journees_total": "566",
      "nb_journees_hc": "566",
      "nb_journees_hp": "0",
      "sexe_ratio": "100%",
      "age_moyen": "10.11",
      "avq_physique": "16",
      "avq_relationnel": "6.86",
      "nb_actes_csarr": "0.52"
    },
    {
      "finess": "720000744",
      "raison_sociale": "SSR CENTRE DE L'ARCHE",
      "categorie": "PSPH/EBNL",
      "periode": "M12",
      "nb_journees_total": "156",
      "nb_journees_hc": "156",
      "nb_journees_hp": "0",
      "sexe_ratio": "26.3%",
      "age_moyen": "7.26",
      "avq_physique": "15.22",
      "avq_relationnel": "7.07",
      "nb_actes_csarr": "9.12"
    },
    {
      "finess": "740780143",
      "raison_sociale": "ÉTABLISSEMENT DE SANTÉ EVIAN - MGEN",
      "categorie": "PSPH/EBNL",
      "periode": "M12",
      "nb_journees_total": "95",
      "nb_journees_hc": "95",
      "nb_journees_hp": "0",
      "sexe_ratio": "25.3%",
      "age_moyen": "13.97",
      "avq_physique": "15.59",
      "avq_relationnel": "7.53",
      "nb_actes_csarr": "2.57"
    },
    {
      "finess": "750712184",
      "raison_sociale": "AP-HP",
      "categorie": "CHR/U",
      "periode": "M12",
      "nb_journees_total": "253",
      "nb_journees_hc": "253",
      "nb_journees_hp": "0",
      "sexe_ratio": "0%",
      "age_moyen": "12.45",
      "avq_physique": "16",
      "avq_relationnel": "8",
      "nb_actes_csarr": "2.68"
    },
    {
      "finess": "760781054",
      "raison_sociale": "LADAPT SEINE MARITIME",
      "categorie": "PSPH/EBNL",
      "periode": "M12",
      "nb_journees_total": "287",
      "nb_journees_hc": "287",
      "nb_journees_hp": "0",
      "sexe_ratio": "33.1%",
      "age_moyen": "8.52",
      "avq_physique": "16",
      "avq_relationnel": "7.57",
      "nb_actes_csarr": "1.83"
    },
    {
      "finess": "770000420",
      "raison_sociale": "CRF ELLEN POIDATZ",
      "categorie": "PSPH/EBNL",
      "periode": "M12",
      "nb_journees_total": "1 à 10",
      "nb_journees_hc": "1 à 10",
      "nb_journees_hp": "0",
      "sexe_ratio": "NA",
      "age_moyen": "NA",
      "avq_physique": "NA",
      "avq_relationnel": "NA",
      "nb_actes_csarr": "NA"
    },
    {
      "finess": "770701225",
      "raison_sociale": "CRRF LE BRASSET",
      "categorie": "PSPH/EBNL",
      "periode": "M12",
      "nb_journees_total": "1 à 10",
      "nb_journees_hc": "1 à 10",
      "nb_journees_hp": "0",
      "sexe_ratio": "NA",
      "age_moyen": "NA",
      "avq_physique": "NA",
      "avq_relationnel": "NA",
      "nb_actes_csarr": "NA"
    },
    {
      "finess": "780630026",
      "raison_sociale": "CENTRE PEDIATRIQUE DES COTES",
      "categorie": "PSPH/EBNL",
      "periode": "M12",
      "nb_journees_total": "46",
      "nb_journees_hc": "46",
      "nb_journees_hp": "0",
      "sexe_ratio": "43.5%",
      "age_moyen": "11.7",
      "avq_physique": "16",
      "avq_relationnel": "8",
      "nb_actes_csarr": "0.54"
    },
    {
      "finess": "800000051",
      "raison_sociale": "CH DE CORBIE",
      "categorie": "CH",
      "periode": "M12",
      "nb_journees_total": "20",
      "nb_journees_hc": "20",
      "nb_journees_hp": "0",
      "sexe_ratio": "90%",
      "age_moyen": "14.1",
      "avq_physique": "12.4",
      "avq_relationnel": "7.1",
      "nb_actes_csarr": "1.9"
    },
    {
      "finess": "830100632",
      "raison_sociale": "INSTITUT REED. FONCT. POMPONIANA OLBIA",
      "categorie": "PSPH/EBNL",
      "periode": "M12",
      "nb_journees_total": "31",
      "nb_journees_hc": "31",
      "nb_journees_hp": "0",
      "sexe_ratio": "0%",
      "age_moyen": "15.19",
      "avq_physique": "16",
      "avq_relationnel": "8",
      "nb_actes_csarr": "0.48"
    },
    {
      "finess": "860014208",
      "raison_sociale": "CHU DE POITIERS",
      "categorie": "CHR/U",
      "periode": "M12",
      "nb_journees_total": "1 à 10",
      "nb_journees_hc": "1 à 10",
      "nb_journees_hp": "0",
      "sexe_ratio": "NA",
      "age_moyen": "NA",
      "avq_physique": "NA",
      "avq_relationnel": "NA",
      "nb_actes_csarr": "NA"
    },
    {
      "finess": "930021431",
      "raison_sociale": "SSR PEDIATRIQUES EPABR MONTREUIL II",
      "categorie": "PSPH/EBNL",
      "periode": "M12",
      "nb_journees_total": "47",
      "nb_journees_hc": "47",
      "nb_journees_hp": "0",
      "sexe_ratio": "0%",
      "age_moyen": "8",
      "avq_physique": "16",
      "avq_relationnel": "8",
      "nb_actes_csarr": "0.68"
    },
    {
      "finess": "940016819",
      "raison_sociale": "HÔPITAUX PARIS EST VAL-DE-MARNE",
      "categorie": "CH",
      "periode": "M12",
      "nb_journees_total": "252",
      "nb_journees_hc": "252",
      "nb_journees_hp": "0",
      "sexe_ratio": "82.9%",
      "age_moyen": "14.48",
      "avq_physique": "15.08",
      "avq_relationnel": "6.82",
      "nb_actes_csarr": "7.2"
    },
    {
      "finess": "970100228",
      "raison_sociale": "CHU DE LA GUADELOUPE",
      "categorie": "CHR/U",
      "periode": "M12",
      "nb_journees_total": "15",
      "nb_journees_hc": "15",
      "nb_journees_hp": "0",
      "sexe_ratio": "100%",
      "age_moyen": "5",
      "avq_physique": "16",
      "avq_relationnel": "8",
      "nb_actes_csarr": "2.4"
    },
    {
      "finess": "970423000",
      "raison_sociale": "HÔPITAL D'ENFANTS",
      "categorie": "PSPH/EBNL",
      "periode": "M12",
      "nb_journees_total": "120",
      "nb_journees_hc": "120",
      "nb_journees_hp": "0",
      "sexe_ratio": "7.5%",
      "age_moyen": "6.83",
      "avq_physique": "16",
      "avq_relationnel": "7.73",
      "nb_actes_csarr": "1.69"
    },
    {
      "finess": "Total",
      "raison_sociale": "Total",
      "categorie": "Total",
      "periode": "Total",
      "nb_journees_total": "6873",
      "nb_journees_hc": "6873",
      "nb_journees_hp": "0",
      "sexe_ratio": "66.2%",
      "age_moyen": "9.93",
      "avq_physique": "15.45",
      "avq_relationnel": "7.39",
      "nb_actes_csarr": "3.42"
    }
  ]
}